{
  "topicId": "data",
  "version": 1,
  "title": "Data Quiz",
  "passMark": 70,
  "shuffleQuestions": true,
  "shuffleOptions": true,
  "questions": [
    {
      "id": "data-q-001",
      "text": "What is digital data?",
      "options": [
        {
          "id": "a",
          "text": "Data stored and processed as binary digits"
        },
        {
          "id": "b",
          "text": "All of the above"
        },
        {
          "id": "c",
          "text": "None of these"
        },
        {
          "id": "d",
          "text": "Only partially correct"
        }
      ],
      "correctOptionId": "a",
      "explanation": "Data stored and processed as binary digits.",
      "tags": [
        "unit1"
      ]
    },
    {
      "id": "data-q-002",
      "text": "What is analogue data?",
      "options": [
        {
          "id": "a",
          "text": "Continuous data, such as sound or light before it is converted into di"
        },
        {
          "id": "b",
          "text": "All of the above"
        },
        {
          "id": "c",
          "text": "None of these"
        },
        {
          "id": "d",
          "text": "Only partially correct"
        }
      ],
      "correctOptionId": "a",
      "explanation": "Continuous data, such as sound or light before it is converted into digital form.",
      "tags": [
        "unit1"
      ]
    },
    {
      "id": "data-q-003",
      "text": "What process converts analogue sound or light into digital form?",
      "options": [
        {
          "id": "a",
          "text": "Analogue to digital conversion, involving recording, sampling and storing"
        },
        {
          "id": "b",
          "text": "All of the above"
        },
        {
          "id": "c",
          "text": "None of these"
        },
        {
          "id": "d",
          "text": "Only partially correct"
        }
      ],
      "correctOptionId": "a",
      "explanation": "Analogue to digital conversion, involving recording, sampling and storing.",
      "tags": [
        "unit1"
      ]
    },
    {
      "id": "data-q-004",
      "text": "Name two advantages of storing data digitally.",
      "options": [
        {
          "id": "a",
          "text": "Examples include easier retrieval, efficiency, security, accessibility"
        },
        {
          "id": "b",
          "text": "All of the above"
        },
        {
          "id": "c",
          "text": "None of these"
        },
        {
          "id": "d",
          "text": "Only partially correct"
        }
      ],
      "correctOptionId": "a",
      "explanation": "Examples include easier retrieval, efficiency, security, accessibility and scalability.",
      "tags": [
        "unit1"
      ]
    },
    {
      "id": "data-q-005",
      "text": "Name two disadvantages of storing data digitally.",
      "options": [
        {
          "id": "a",
          "text": "Examples include loss of quality due to sampling, expense and management issues"
        },
        {
          "id": "b",
          "text": "All of the above"
        },
        {
          "id": "c",
          "text": "None of these"
        },
        {
          "id": "d",
          "text": "Only partially correct"
        }
      ],
      "correctOptionId": "a",
      "explanation": "Examples include loss of quality due to sampling, expense and management issues.",
      "tags": [
        "unit1"
      ]
    },
    {
      "id": "data-q-006",
      "text": "What is a pixel?",
      "options": [
        {
          "id": "a",
          "text": "A basic element used to store/display a digital image"
        },
        {
          "id": "b",
          "text": "All of the above"
        },
        {
          "id": "c",
          "text": "None of these"
        },
        {
          "id": "d",
          "text": "Only partially correct"
        }
      ],
      "correctOptionId": "a",
      "explanation": "A basic element used to store/display a digital image.",
      "tags": [
        "unit1"
      ]
    },
    {
      "id": "data-q-007",
      "text": "What does resolution relate to?",
      "options": [
        {
          "id": "a",
          "text": "The level of detail in a digital image"
        },
        {
          "id": "b",
          "text": "All of the above"
        },
        {
          "id": "c",
          "text": "None of these"
        },
        {
          "id": "d",
          "text": "Only partially correct"
        }
      ],
      "correctOptionId": "a",
      "explanation": "The level of detail in a digital image.",
      "tags": [
        "unit1"
      ]
    },
    {
      "id": "data-q-008",
      "text": "Name two types of digital graphics.",
      "options": [
        {
          "id": "a",
          "text": "Vector graphics and bitmap graphics"
        },
        {
          "id": "b",
          "text": "All of the above"
        },
        {
          "id": "c",
          "text": "None of these"
        },
        {
          "id": "d",
          "text": "Only partially correct"
        }
      ],
      "correctOptionId": "a",
      "explanation": "Vector graphics and bitmap graphics.",
      "tags": [
        "unit1"
      ]
    }
  ]
}